papyrus/__init__.py
papyrus/_shapely_utils.py
papyrus/geo_interface.py
papyrus/geojsonencoder.py
papyrus/protocol.py
papyrus/renderers.py
papyrus/tests/__init__.py
papyrus/tests/test_geo_interface.py
papyrus/tests/test_init.py
papyrus/tests/test_protocol.py
papyrus/tests/test_renderers.py
papyrus/tests/views.py
papyrus/xsd.py
papyrus-2.6.2.dist-info/LICENSE.txt
papyrus-2.6.2.dist-info/METADATA
papyrus-2.6.2.dist-info/WHEEL
papyrus-2.6.2.dist-info/entry_points.txt
papyrus-2.6.2.dist-info/RECORD
